fastagentic/__init__.py
fastagentic/app.py
fastagentic/context.py
fastagentic/decorators.py
fastagentic/py.typed
fastagentic/types.py
fastagentic/adapters/__init__.py
fastagentic/adapters/autogen.py
fastagentic/adapters/base.py
fastagentic/adapters/crewai.py
fastagentic/adapters/dspy.py
fastagentic/adapters/langchain.py
fastagentic/adapters/langgraph.py
fastagentic/adapters/llamaindex.py
fastagentic/adapters/pydanticai.py
fastagentic/adapters/sdk.py
fastagentic/adapters/semantic_kernel.py
fastagentic/audit/__init__.py
fastagentic/audit/hooks.py
fastagentic/audit/logger.py
fastagentic/checkpoint/__init__.py
fastagentic/checkpoint/base.py
fastagentic/checkpoint/stores.py
fastagentic/cli/__init__.py
fastagentic/cli/agent.py
fastagentic/cli/config_cli.py
fastagentic/cli/main.py
fastagentic/cli/templates.py
fastagentic/cluster/__init__.py
fastagentic/cluster/coordinator.py
fastagentic/cluster/task.py
fastagentic/cluster/worker.py
fastagentic/compliance/__init__.py
fastagentic/compliance/hooks.py
fastagentic/compliance/pii.py
fastagentic/cost/__init__.py
fastagentic/cost/hooks.py
fastagentic/cost/tracker.py
fastagentic/dashboard/__init__.py
fastagentic/dashboard/api.py
fastagentic/dashboard/metrics.py
fastagentic/dashboard/stats.py
fastagentic/durability/__init__.py
fastagentic/durability/checkpoint.py
fastagentic/durability/store.py
fastagentic/hitl/__init__.py
fastagentic/hitl/approval.py
fastagentic/hitl/confirmation.py
fastagentic/hitl/escalation.py
fastagentic/hooks/__init__.py
fastagentic/hooks/base.py
fastagentic/integrations/__init__.py
fastagentic/integrations/base.py
fastagentic/integrations/lakera.py
fastagentic/integrations/langfuse.py
fastagentic/integrations/mem0.py
fastagentic/integrations/portkey.py
fastagentic/memory/__init__.py
fastagentic/memory/base.py
fastagentic/memory/redis.py
fastagentic/ops/__init__.py
fastagentic/ops/readiness.py
fastagentic/policy/__init__.py
fastagentic/policy/base.py
fastagentic/policy/budget.py
fastagentic/policy/engine.py
fastagentic-1.0.0.dist-info/METADATA
fastagentic-1.0.0.dist-info/WHEEL
fastagentic-1.0.0.dist-info/entry_points.txt
fastagentic-1.0.0.dist-info/RECORD
