Metadata-Version: 2.4
Name: fastagentic
Version: 1.0.0
Summary: The deployment layer for agentic applications. Build agents with anything. Ship them with FastAgentic.
Project-URL: Homepage, https://github.com/fastagentic/fastagentic
Project-URL: Documentation, https://fastagentic.dev
Project-URL: Repository, https://github.com/fastagentic/fastagentic
Author: FastAgentic Team
License: MIT
Keywords: a2a,agents,ai,deployment,fastapi,llm,mcp
Classifier: Development Status :: 3 - Alpha
Classifier: Intended Audience :: Developers
Classifier: License :: OSI Approved :: MIT License
Classifier: Programming Language :: Python :: 3
Classifier: Programming Language :: Python :: 3.10
Classifier: Programming Language :: Python :: 3.11
Classifier: Programming Language :: Python :: 3.12
Classifier: Topic :: Scientific/Engineering :: Artificial Intelligence
Classifier: Topic :: Software Development :: Libraries :: Python Modules
Requires-Python: >=3.10
Requires-Dist: aiofiles<24.0.0,>=23.2.0
Requires-Dist: anyio<5.0.0,>=4.7.0
Requires-Dist: fastapi<2.0.0,>=0.115.0
Requires-Dist: httpx<1.0.0,>=0.28.0
Requires-Dist: pydantic-settings<3.0.0,>=2.6.0
Requires-Dist: pydantic<3.0.0,>=2.10.0
Requires-Dist: rich<14.0.0,>=13.9.0
Requires-Dist: sse-starlette<3.0.0,>=2.2.0
Requires-Dist: structlog<25.0.0,>=24.4.0
Requires-Dist: typer<1.0.0,>=0.15.0
Requires-Dist: uvicorn[standard]<1.0.0,>=0.32.0
Provides-Extra: adapters
Requires-Dist: crewai>=0.86.0; extra == 'adapters'
Requires-Dist: langchain-core>=0.3.0; extra == 'adapters'
Requires-Dist: langchain>=0.3.0; extra == 'adapters'
Requires-Dist: langgraph>=0.2.0; extra == 'adapters'
Requires-Dist: pydantic-ai>=0.0.30; extra == 'adapters'
Provides-Extra: all
Requires-Dist: crewai>=0.86.0; extra == 'all'
Requires-Dist: httpx>=0.28.0; extra == 'all'
Requires-Dist: langchain-core>=0.3.0; extra == 'all'
Requires-Dist: langchain>=0.3.0; extra == 'all'
Requires-Dist: langfuse>=2.57.0; extra == 'all'
Requires-Dist: langgraph>=0.2.0; extra == 'all'
Requires-Dist: mem0ai>=0.1.0; extra == 'all'
Requires-Dist: opentelemetry-api>=1.29.0; extra == 'all'
Requires-Dist: opentelemetry-exporter-otlp>=1.29.0; extra == 'all'
Requires-Dist: opentelemetry-instrumentation-fastapi>=0.50b0; extra == 'all'
Requires-Dist: opentelemetry-sdk>=1.29.0; extra == 'all'
Requires-Dist: portkey-ai>=1.9.0; extra == 'all'
Requires-Dist: pydantic-ai>=0.0.30; extra == 'all'
Requires-Dist: redis>=5.2.0; extra == 'all'
Provides-Extra: braintrust
Requires-Dist: braintrust>=0.0.170; extra == 'braintrust'
Provides-Extra: crewai
Requires-Dist: crewai>=0.86.0; extra == 'crewai'
Provides-Extra: dev
Requires-Dist: httpx>=0.28.0; extra == 'dev'
Requires-Dist: mypy>=1.13.0; extra == 'dev'
Requires-Dist: pre-commit>=4.0.0; extra == 'dev'
Requires-Dist: pytest-asyncio>=0.24.0; extra == 'dev'
Requires-Dist: pytest-cov>=6.0.0; extra == 'dev'
Requires-Dist: pytest>=8.3.0; extra == 'dev'
Requires-Dist: ruff>=0.8.0; extra == 'dev'
Provides-Extra: docs
Requires-Dist: mike>=2.1.0; extra == 'docs'
Requires-Dist: mkdocs-material>=9.5.0; extra == 'docs'
Requires-Dist: mkdocs-minify-plugin>=0.8.0; extra == 'docs'
Requires-Dist: mkdocs>=1.6.0; extra == 'docs'
Provides-Extra: integrations
Requires-Dist: httpx>=0.28.0; extra == 'integrations'
Requires-Dist: langfuse>=2.57.0; extra == 'integrations'
Requires-Dist: mem0ai>=0.1.0; extra == 'integrations'
Requires-Dist: portkey-ai>=1.9.0; extra == 'integrations'
Provides-Extra: lakera
Requires-Dist: httpx>=0.28.0; extra == 'lakera'
Provides-Extra: langchain
Requires-Dist: langchain-core>=0.3.0; extra == 'langchain'
Requires-Dist: langchain>=0.3.0; extra == 'langchain'
Provides-Extra: langfuse
Requires-Dist: langfuse>=2.57.0; extra == 'langfuse'
Provides-Extra: langgraph
Requires-Dist: langchain-core>=0.3.0; extra == 'langgraph'
Requires-Dist: langgraph>=0.2.0; extra == 'langgraph'
Provides-Extra: mem0
Requires-Dist: mem0ai>=0.1.0; extra == 'mem0'
Provides-Extra: otel
Requires-Dist: opentelemetry-api>=1.29.0; extra == 'otel'
Requires-Dist: opentelemetry-exporter-otlp>=1.29.0; extra == 'otel'
Requires-Dist: opentelemetry-instrumentation-fastapi>=0.50b0; extra == 'otel'
Requires-Dist: opentelemetry-sdk>=1.29.0; extra == 'otel'
Provides-Extra: portkey
Requires-Dist: portkey-ai>=1.9.0; extra == 'portkey'
Provides-Extra: postgres
Requires-Dist: asyncpg>=0.30.0; extra == 'postgres'
Requires-Dist: sqlalchemy>=2.0.0; extra == 'postgres'
Provides-Extra: pydanticai
Requires-Dist: pydantic-ai>=0.0.30; extra == 'pydanticai'
Provides-Extra: redis
Requires-Dist: redis>=5.2.0; extra == 'redis'
Provides-Extra: testing
Requires-Dist: faker>=24.0.0; extra == 'testing'
Requires-Dist: hypothesis-jsonschema>=0.23.0; extra == 'testing'
Requires-Dist: hypothesis>=6.100.0; extra == 'testing'
Requires-Dist: mutmut>=2.4.0; extra == 'testing'
Requires-Dist: pytest-asyncio>=0.24.0; extra == 'testing'
Requires-Dist: pytest-benchmark>=4.0.0; extra == 'testing'
Requires-Dist: pytest-timeout>=2.3.0; extra == 'testing'
